Metadata-Version: 1.1
Name: django-permanent
Version: 1.1.4
Summary: Yet another approach to provide soft (logical) delete or masking (thrashing) django models instead of deleting them physically from db.
Home-page: https://github.com/meteozond/django-permanent
Author: Alexander Klimenko
Author-email: alex@erix.ru
License: BSD
Keywords: django,delete,undelete,safedelete,remove,restore,softdelete,logicaldelete,trash
Platform: UNKNOWN
Classifier: Framework :: Django
Classifier: Intended Audience :: Developers
Classifier: Intended Audience :: System Administrators
Classifier: Operating System :: OS Independent
Classifier: Topic :: Software Development
Classifier: Programming Language :: Python :: 2.7
Classifier: Programming Language :: Python :: 3.4
Classifier: Programming Language :: Python :: 3.5
Classifier: Development Status :: 4 - Beta
Classifier: License :: OSI Approved :: BSD License
